starlette_precompressed_static/__init__.py
starlette_precompressed_static/py.typed
starlette_precompressed_static/starlette_precompressed_static.py
starlette_precompressed_static-2022.10.13.dist-info/METADATA
starlette_precompressed_static-2022.10.13.dist-info/WHEEL
starlette_precompressed_static-2022.10.13.dist-info/licenses/LICENCE
starlette_precompressed_static-2022.10.13.dist-info/RECORD
