Metadata-Version: 2.1
Name: starlette-precompressed-static
Version: 2022.10.13
Summary: A small library for Starlette, to serve pre-compressed static resources
Project-URL: Homepage, https://github.com/magnuswatn/starlette-precompressed-static
Author-email: Magnus Watn <magnus@watn.no>
License-File: LICENCE
Keywords: brotli,gzip,pre-compressed,resources,starlette,static
Classifier: License :: OSI Approved :: MIT License
Classifier: Operating System :: OS Independent
Classifier: Programming Language :: Python
Classifier: Programming Language :: Python :: 3
Classifier: Programming Language :: Python :: 3.9
Classifier: Programming Language :: Python :: 3.10
Classifier: Programming Language :: Python :: 3.11
Requires-Python: >=3.9
Requires-Dist: starlette
Provides-Extra: test
Requires-Dist: httpx; extra == 'test'
Requires-Dist: pytest; extra == 'test'
